MANIFEST.in
README.md
setup.py
PyTerminalCommander/__init__.py
PyTerminalCommander.egg-info/PKG-INFO
PyTerminalCommander.egg-info/SOURCES.txt
PyTerminalCommander.egg-info/dependency_links.txt
PyTerminalCommander.egg-info/requires.txt
PyTerminalCommander.egg-info/top_level.txt