Metadata-Version: 1.1
Name: PyTerminalCommander
Version: 0.0.4
Summary: A library use to build command-to-output Shell GUI application.
Home-page: https://github.com/owwlo/PyTerminalCommander
Author: owwlo
Author-email: owwlo.g@gmail.com
License: MIT
Download-URL: https://github.com/owwlo/PyTerminalCommander/tarball/0.0.4
Keywords: shell gui command commander output log logger
Platform: UNKNOWN
Classifier: Development Status :: 3 - Alpha
Classifier: Intended Audience :: Developers
Classifier: Topic :: Software Development :: Libraries :: Python Modules
Classifier: License :: OSI Approved :: MIT License
Classifier: Programming Language :: Python :: 2
Classifier: Programming Language :: Python :: 2.6
Classifier: Programming Language :: Python :: 2.7
Classifier: Programming Language :: Python :: 3
Classifier: Programming Language :: Python :: 3.3
Classifier: Programming Language :: Python :: 3.4
Classifier: Programming Language :: Python :: 3.5
